numpy_demo/LICENSE.txt
numpy_demo/__config__.py
numpy_demo/__init__.py
numpy_demo/_distributor_init.py
numpy_demo/_globals.py
numpy_demo/_pytesttester.py
numpy_demo/conftest.py
numpy_demo/ctypeslib.py
numpy_demo/dual.py
numpy_demo/matlib.py
numpy_demo/setup.py
numpy_demo/version.py
numpy_demo/compat/__init__.py
numpy_demo/compat/_inspect.py
numpy_demo/compat/py3k.py
numpy_demo/compat/setup.py
numpy_demo/compat/tests/__init__.py
numpy_demo/compat/tests/test_compat.py
numpy_demo/core/__init__.py
numpy_demo/core/_add_newdocs.py
numpy_demo/core/_asarray.py
numpy_demo/core/_dtype.py
numpy_demo/core/_dtype_ctypes.py
numpy_demo/core/_exceptions.py
numpy_demo/core/_internal.py
numpy_demo/core/_methods.py
numpy_demo/core/_multiarray_tests.cpython-37m-aarch64-linux-gnu.so
numpy_demo/core/_multiarray_umath.cpython-37m-aarch64-linux-gnu.so
numpy_demo/core/_operand_flag_tests.cpython-37m-aarch64-linux-gnu.so
numpy_demo/core/_rational_tests.cpython-37m-aarch64-linux-gnu.so
numpy_demo/core/_string_helpers.py
numpy_demo/core/_struct_ufunc_tests.cpython-37m-aarch64-linux-gnu.so
numpy_demo/core/_type_aliases.py
numpy_demo/core/_ufunc_config.py
numpy_demo/core/_umath_tests.cpython-37m-aarch64-linux-gnu.so
numpy_demo/core/arrayprint.py
numpy_demo/core/cversions.py
numpy_demo/core/defchararray.py
numpy_demo/core/einsumfunc.py
numpy_demo/core/fromnumeric.py
numpy_demo/core/function_base.py
numpy_demo/core/generate_numpy_demo_api.py
numpy_demo/core/getlimits.py
numpy_demo/core/machar.py
numpy_demo/core/memmap.py
numpy_demo/core/multiarray.py
numpy_demo/core/numeric.py
numpy_demo/core/numerictypes.py
numpy_demo/core/overrides.py
numpy_demo/core/records.py
numpy_demo/core/setup.py
numpy_demo/core/setup_common.py
numpy_demo/core/shape_base.py
numpy_demo/core/umath.py
numpy_demo/core/umath_tests.py
numpy_demo/core/include/numpy_demo/__multiarray_api.h
numpy_demo/core/include/numpy_demo/__ufunc_api.h
numpy_demo/core/include/numpy_demo/_neighborhood_iterator_imp.h
numpy_demo-1.23.0.dist-info/LICENSE.txt
numpy_demo-1.23.0.dist-info/LICENSES_bundled.txt
numpy_demo-1.23.0.dist-info/METADATA
numpy_demo-1.23.0.dist-info/WHEEL
numpy_demo-1.23.0.dist-info/entry_points.txt
numpy_demo-1.23.0.dist-info/top_level.txt
numpy_demo-1.23.0.dist-info/RECORD
