Metadata-Version: 2.1
Name: numpy-demo
Version: 1.23.0
Summary: NumPy-demo is a test package and is a clone of numpy.
Home-page: https://www.numpy_demo.org
Author: Travis E. Oliphant et al.
Maintainer: NumPy Developers
Maintainer-email: numpy_demo-discussion@python.org
License: BSD
Download-URL: https://pypi.python.org/pypi/numpy_demo
Project-URL: Bug Tracker, https://github.com/numpy_demo/numpy_demo/issues
Project-URL: Documentation, https://docs.scipy.org/doc/numpy_demo/
Project-URL: Source Code, https://github.com/numpy_demo/numpy_demo
Platform: Windows
Platform: Linux
Platform: Solaris
Platform: Mac OS-X
Platform: Unix
Classifier: Development Status :: 5 - Production/Stable
Classifier: Intended Audience :: Science/Research
Classifier: Intended Audience :: Developers
Classifier: License :: OSI Approved
Classifier: Programming Language :: C
Classifier: Programming Language :: Python
Classifier: Programming Language :: Python :: 3
Classifier: Programming Language :: Python :: 3.6
Classifier: Programming Language :: Python :: 3.7
Classifier: Programming Language :: Python :: 3.8
Classifier: Programming Language :: Python :: 3 :: Only
Classifier: Programming Language :: Python :: Implementation :: CPython
Classifier: Topic :: Software Development
Classifier: Topic :: Scientific/Engineering
Classifier: Operating System :: Microsoft :: Windows
Classifier: Operating System :: POSIX
Classifier: Operating System :: Unix
Classifier: Operating System :: MacOS
Requires-Python: >=3.5
